AUTHORS
LICENSE
MANIFEST.in
README.md
requirements_production.txt
setup.py
openslides_voting/__init__.py
openslides_voting/access_permissions.py
openslides_voting/apps.py
openslides_voting/config_variables.py
openslides_voting/models.py
openslides_voting/projector.py
openslides_voting/serializers.py
openslides_voting/signals.py
openslides_voting/urls.py
openslides_voting/views.py
openslides_voting/voting.py
openslides_voting.egg-info/PKG-INFO
openslides_voting.egg-info/SOURCES.txt
openslides_voting.egg-info/dependency_links.txt
openslides_voting.egg-info/entry_points.txt
openslides_voting.egg-info/requires.txt
openslides_voting.egg-info/top_level.txt
openslides_voting/locale/readme.txt
openslides_voting/locale/angular-gettext/de.po
openslides_voting/locale/angular-gettext/template-en.pot
openslides_voting/locale/de/LC_MESSAGES/django.mo
openslides_voting/locale/de/LC_MESSAGES/django.po
openslides_voting/locale/en/LC_MESSAGES/django.po
openslides_voting/management/__init__.py
openslides_voting/management/commands/__init__.py
openslides_voting/management/commands/attending.py
openslides_voting/migrations/0001_initial.py
openslides_voting/migrations/__init__.py
openslides_voting/static/i18n/openslides_voting/de.json
openslides_voting/static/img/button-interact-abstain.png
openslides_voting/static/img/button-interact-no.png
openslides_voting/static/img/button-interact-yes.png
openslides_voting/static/js/openslides_voting/base.js
openslides_voting/static/js/openslides_voting/libs.js
openslides_voting/static/js/openslides_voting/pdf.js
openslides_voting/static/js/openslides_voting/projector.js
openslides_voting/static/js/openslides_voting/site.js
openslides_voting/static/js/openslides_voting/templatehooks.js
openslides_voting/static/js/openslides_voting/templates.js
openslides_voting/static/templates/openslides_voting/absentee-vote-form.html
openslides_voting/static/templates/openslides_voting/absentee-vote-import.html
openslides_voting/static/templates/openslides_voting/absentee-vote-list.html
openslides_voting/static/templates/openslides_voting/assignment-poll-detail.html
openslides_voting/static/templates/openslides_voting/assignment-poll-form-buttons-hook.html
