Metadata-Version: 2.1
Name: openslides-voting
Version: 3.1
Summary: OpenSlides Voting Plugin
Home-page: https://github.com/OpenSlides/openslides-voting
Author: Authors of OpenSlides Voting Plugin, see AUTHORS
Author-email: support@openslides.org
License: MIT
Keywords: OpenSlides
Platform: UNKNOWN
Classifier: Development Status :: 5 - Production/Stable
Classifier: Environment :: Plugins
Classifier: Environment :: Web Environment
Classifier: Framework :: Django
Classifier: License :: OSI Approved :: MIT License
Classifier: Operating System :: OS Independent
Classifier: Programming Language :: Python :: 3.5
Classifier: Programming Language :: Python :: 3.6
Classifier: Programming Language :: Python :: 3.7
